shajon/__init__.py
shajon/jsonxd.py
shajon-0.1.2.dist-info/METADATA
shajon-0.1.2.dist-info/WHEEL
shajon-0.1.2.dist-info/top_level.txt
shajon-0.1.2.dist-info/RECORD
