Metadata-Version: 2.2
Name: shajon
Version: 0.1.2
Summary: A module that checks and downloads required shared object files [JSON XD and others tool sequrity files].
Home-page: https://github.com/SHAJON-404/SHAJON
Author: SHAH MAKHDUM SHAJON
Author-email: shahmakhdumshajon@gmail.com
Classifier: Programming Language :: Python :: 3
Classifier: License :: OSI Approved :: MIT License
Classifier: Operating System :: OS Independent
Requires-Python: >=3.6
Dynamic: author
Dynamic: author-email
Dynamic: classifier
Dynamic: home-page
Dynamic: requires-python
Dynamic: summary
